aws_empty_ecr_repository/__init__.py
aws_empty_ecr_repository/empty_ecr_repository.py
aws_empty_ecr_repository/package/__init__.py
aws_empty_ecr_repository/package/action.py
aws_empty_ecr_repository/package/cfnresponse.py
aws_empty_ecr_repository/package/index.py
aws_empty_ecr_repository-1.3.0.dist-info/LICENSE
aws_empty_ecr_repository-1.3.0.dist-info/METADATA
aws_empty_ecr_repository-1.3.0.dist-info/WHEEL
aws_empty_ecr_repository-1.3.0.dist-info/top_level.txt
aws_empty_ecr_repository-1.3.0.dist-info/RECORD
